CHANGES.txt
LICENSE.txt
MANIFEST.in
PackageInfo.cfg
README.rst
_dist_
setup.cfg
setup.py
html/genindex.html
html/index.html
html/objects.inv
html/py-modindex.html
html/search.html
html/searchindex.js
html/_sources/index.txt
html/_static/ajax-loader.gif
html/_static/basic.css
html/_static/comment-bright.png
html/_static/comment-close.png
html/_static/comment.png
html/_static/default.css
html/_static/doctools.js
html/_static/down-pressed.png
html/_static/down.png
html/_static/file.png
html/_static/jquery.js
html/_static/minus.png
html/_static/plus.png
html/_static/pygments.css
html/_static/searchtools.js
html/_static/sidebar.js
html/_static/underscore.js
html/_static/up-pressed.png
html/_static/up.png
html/_static/websupport.js
pyfscache/__init__.py
pyfscache/_version.py
pyfscache/fscache.py
pyfscache.egg-info/PKG-INFO
pyfscache.egg-info/SOURCES.txt
pyfscache.egg-info/dependency_links.txt
pyfscache.egg-info/top_level.txt
pyfscache/tests/__init__.py
pyfscache/tests/test_fscache.py