Metadata-Version: 1.1
Name: pyfscache
Version: 0.9.12
Summary: A file system cache for python.
Home-page: http://pyfscache.bravais.net
Author: James C. Stroud
Author-email: jstroud@mbi.ucla.edu
License: BSD
Platform: UNKNOWN
Classifier: Programming Language :: Python :: 2.5
Classifier: Programming Language :: Python :: 2.6
Classifier: Programming Language :: Python :: 2.7
